score.auth-0.7.1-py3.7-nspkg.pth
score/auth/__init__.py
score/auth/_init.py
score/auth/_ruleset.py
score/auth/authenticator.py
score.auth-0.7.1.dist-info/COPYING.LESSER.txt
score.auth-0.7.1.dist-info/METADATA
score.auth-0.7.1.dist-info/WHEEL
score.auth-0.7.1.dist-info/namespace_packages.txt
score.auth-0.7.1.dist-info/top_level.txt
score.auth-0.7.1.dist-info/RECORD
