Metadata-Version: 2.1
Name: score.auth
Version: 0.7.1
Summary: Authorization and Authentication for The SCORE Framework
Home-page: http://strg.at
Author: strg.at
Author-email: support@strg.at
License: LGPL
Keywords: score framework authentication authorization pyramid
Platform: UNKNOWN
Classifier: Development Status :: 4 - Beta
Classifier: Environment :: Console
Classifier: Environment :: Web Environment
Classifier: Framework :: Pyramid
Classifier: Intended Audience :: Developers
Classifier: License :: OSI Approved :: GNU Lesser General Public License v3 or later (LGPLv3+)
Classifier: Operating System :: OS Independent
Classifier: Programming Language :: Python :: 3
Classifier: Programming Language :: Python :: 3.4
Classifier: Programming Language :: Python :: 3.5
Classifier: Topic :: Security
Classifier: Topic :: Software Development :: Libraries :: Application Frameworks
Requires-Dist: score.init (>=0.3)
Requires-Dist: score.ctx (<0.7,>=0.6)
